exutil
tests
