Metadata-Version: 2.1
Name: exutil
Version: 0.3.2
Summary: Utility for managing exercism workflow.
Home-page: https://github.com/cmccandless/exutil
Author: Corey McCandless
Author-email: crm1994@gmail.com
License: UNKNOWN
Platform: UNKNOWN
Classifier: Programming Language :: Python :: 3
Classifier: License :: OSI Approved :: MIT License
Classifier: Operating System :: OS Independent
